{
  "commits": [
    {
      "hash": "e22e9bc14795f093634e18baabf97668f32cc302",
      "subtask_id": "subtask-1-1",
      "timestamp": "2026-02-05T01:59:46.313528"
    },
    {
      "hash": "58cee38e4b99148627002fdc41ce8b142a3991ad",
      "subtask_id": "subtask-1-2",
      "timestamp": "2026-02-05T02:02:02.979587"
    },
    {
      "hash": "5cdb418fc7111940504b6c6bfb2102386eb7f8b2",
      "subtask_id": "subtask-2-1",
      "timestamp": "2026-02-05T02:09:45.206594"
    },
    {
      "hash": "c142f7c5f6e9c00ff4040af02bf341549b05791c",
      "subtask_id": "subtask-2-2",
      "timestamp": "2026-02-05T02:11:28.791080"
    }
  ],
  "last_good_commit": "c142f7c5f6e9c00ff4040af02bf341549b05791c",
  "metadata": {
    "created_at": "2026-02-05T01:54:02.488549",
    "last_updated": "2026-02-05T02:11:28.791096"
  }
}